aiges/__init__.py
aiges/__main__.py
aiges/aiges_inner/README.md
aiges/aiges_inner/__init__.py
aiges/aiges_inner/ai.proto
aiges/aiges_inner/ai_service.proto
aiges/aiges_inner/aiges_inner.proto
aiges/aiges_inner/aiges_inner_pb2.py
aiges/aiges_inner/aiges_inner_pb2_grpc.py
aiges/aiges_inner/grpc_stdio.proto
aiges/aiges_inner/grpc_stdio_pb2.py
aiges/aiges_inner/grpc_stdio_pb2_grpc.py
aiges/backend/__init__.py
aiges/backup/demo.json
aiges/backup/wrapper_mmocr.py
aiges/backup/wrapper_old.py
aiges/call_wrapper.py
aiges/callback.py
aiges/client/Readme.md
aiges/client/__init__.py
aiges/client/client.py
aiges/client/utils/aipass_client.py
aiges/client/utils/exception.py
aiges/client/utils/ne_utils.py
aiges/client.py
aiges/cmd/__init__.py
aiges/cmd/config.py
aiges/cmd/create.py
aiges/cmd/package.py
aiges/cmd/root.py
aiges/concurrent/__init__.py
aiges/concurrent/fixpool.py
aiges/concurrent/pool.py
aiges/context/__init__.py
aiges/context/context.py
aiges/core/aiges_methods.py
aiges/core/metadata.py
aiges/core/rest.py
aiges/core/types.py
aiges/dto.py
aiges/errors.py
aiges/examples/once/mmocr/wrapper.py
aiges/examples/stream/mmocr/wrapper.py
aiges/examples/stream/mock/wrapper.py
aiges/gradio_util/__init__.py
aiges/gradio_util/component.py
aiges/out.json
aiges/protocol/struct.py
aiges/protocol/xsf.proto
aiges/protocol/xsf_pb2.py
aiges/protocol/xsf_pb2.pyi
aiges/protocol/xsf_pb2_grpc.py
aiges/protocol/xsfcli.py
aiges/schema/aischema.py
aiges/schema/types.py
aiges/schema/utils/schemaUtils.py
aiges/sdk.py
aiges/serve.py
aiges/serve_new.py
aiges/server.py
aiges/server2.py
aiges/stream.py
aiges/test_data/flask_restx_test.py
aiges/test_data/ok.json
aiges/test_data/origin.json
aiges/test_data/pydantic_test.py
aiges/test_data/test.png
aiges/test_data/testschma.json
aiges/tests/class_func/test_class.py
aiges/tests/class_func/test_queue.py
aiges/tests/shared_memory/pick_utils.py
aiges/tests/shared_memory/test_pickle5.py
aiges/tests/shared_memory/test_pickle5_2.py
aiges-0.16.0.dist-info/LICENSE
aiges-0.16.0.dist-info/METADATA
aiges-0.16.0.dist-info/WHEEL
aiges-0.16.0.dist-info/RECORD
