Metadata-Version: 2.1
Name: aiges
Version: 0.16.0
Summary: A module for test aiges's python wrapper.py
License: Apache License Version 2.0
Author: maybaby
Author-email: ybyang7@iflytek.com
Requires-Python: >=3.6
Classifier: License :: Other/Proprietary License
Classifier: Programming Language :: Python :: 3
Classifier: Programming Language :: Python :: 3.6
Classifier: Programming Language :: Python :: 3.7
Classifier: Programming Language :: Python :: 3.8
Classifier: Programming Language :: Python :: 3.9
Classifier: Programming Language :: Python :: 3.10
Classifier: Programming Language :: Python :: 3.11
Classifier: Programming Language :: Python :: 3.12
Requires-Dist: Flask (==2.2.5)
Requires-Dist: flask_restx (>=1.0.0)
Requires-Dist: gradio (>=3.0)
Requires-Dist: grpcio (>=1.50.0)
Requires-Dist: grpcio-health-checking (>=1.50.0)
Requires-Dist: grpcio-tools (>=1.50.0)
Requires-Dist: jinja2 (>=2.0)
Requires-Dist: jsonref (>=1.0.0)
Requires-Dist: plumbum (>=1.7.0)
Requires-Dist: protobuf (>=3.19)
Requires-Dist: pydantic (>=2.0)
